orderedbunch/__init__.py
orderedbunch/_version.py
orderedbunch/bunch.py
orderedbunch/test.py
orderedbunch-1.0.1.dist-info/METADATA
orderedbunch-1.0.1.dist-info/RECORD
orderedbunch-1.0.1.dist-info/WHEEL
orderedbunch-1.0.1.dist-info/top_level.txt
