Metadata-Version: 2.1
Name: orderedbunch
Version: 1.0.1
Summary: Tab completable ordered dictionary.
Home-page: UNKNOWN
Author: Nathan Longbotham
Author-email: longbotham@gmail.com
License: UNKNOWN
Platform: UNKNOWN
